setup.py
dvc_adapter/__init__.py
dvc_adapter/adapter.py
dvc_adapter/dataclasses.py
dvc_adapter/handler.py
dvc_adapter/logger.py
dvc_adapter/oddrn.py
dvc_adapter/utils.py
dvc_adapter.egg-info/PKG-INFO
dvc_adapter.egg-info/SOURCES.txt
dvc_adapter.egg-info/dependency_links.txt
dvc_adapter.egg-info/entry_points.txt
dvc_adapter.egg-info/not-zip-safe
dvc_adapter.egg-info/requires.txt
dvc_adapter.egg-info/top_level.txt